workspace/__init__.py
workspace/__main__.py
workspace/cli/__init__.py
workspace/cli/callbacks.py
workspace/cli/commands/__init__.py
workspace/cli/commands/add.py
workspace/cli/commands/dependees.py
workspace/cli/commands/dependencies.py
workspace/cli/commands/info.py
workspace/cli/commands/init.py
workspace/cli/commands/list.py
workspace/cli/commands/new.py
workspace/cli/commands/plugin.py
workspace/cli/commands/remove.py
workspace/cli/commands/reverse.py
workspace/cli/commands/run.py
workspace/cli/commands/sync.py
workspace/cli/commands/template/__init__.py
workspace/cli/commands/template/list.py
workspace/cli/commands/template/path.py
workspace/cli/exceptions.py
workspace/cli/runner.py
workspace/cli/theme.py
workspace/cli/utils.py
workspace/core/__init__.py
workspace/core/adapter/__init__.py
workspace/core/adapter/base.py
workspace/core/adapter/pipenv.py
workspace/core/adapter/poetry.py
workspace/core/exceptions.py
workspace/core/models.py
workspace/core/settings.py
workspace/core/templates.py
workspace/py.typed
workspace/templates/pipenv/cookiecutter.json
workspace/templates/pipenv/{{ cookiecutter.project_slug }}/Pipfile
workspace/templates/pipenv/{{ cookiecutter.project_slug }}/README.md
workspace/templates/pipenv/{{ cookiecutter.project_slug }}/{{ cookiecutter.package_name }}/__init__.py
workspace/templates/poetry/cookiecutter.json
workspace/templates/poetry/{{ cookiecutter.project_slug }}/README.md
workspace/templates/poetry/{{ cookiecutter.project_slug }}/poetry.toml
workspace/templates/poetry/{{ cookiecutter.project_slug }}/pyproject.toml
workspace/templates/poetry/{{ cookiecutter.project_slug }}/{{ cookiecutter.package_name }}/__init__.py
workspace_cli-0.3.1.dist-info/entry_points.txt
workspace_cli-0.3.1.dist-info/LICENSE.txt
workspace_cli-0.3.1.dist-info/WHEEL
workspace_cli-0.3.1.dist-info/METADATA
workspace_cli-0.3.1.dist-info/RECORD
