Metadata-Version: 2.1
Name: workspace-cli
Version: 0.3.1
Summary: Manage interdependent projects in a workspace.
Home-page: https://github.com/jacksmith15/workspace-cli
Author: Jack Smith
Requires-Python: >=3.8,<4.0
Classifier: Programming Language :: Python :: 3
Classifier: Programming Language :: Python :: 3.10
Classifier: Programming Language :: Python :: 3.8
Classifier: Programming Language :: Python :: 3.9
Provides-Extra: cookiecutter
Provides-Extra: pipenv
Provides-Extra: poetry
Requires-Dist: click (>=8.0,<9.0)
Requires-Dist: cookiecutter (>=1.7.3,<2.0.0); extra == "cookiecutter"
Requires-Dist: jsonschema (>=4.0.1,<5.0.0)
Requires-Dist: pipenv (>=2021.5.29,<2022.0.0); extra == "pipenv"
Requires-Dist: poetry (>=1.1.11,<2.0.0); extra == "poetry"
Project-URL: Repository, https://github.com/jacksmith15/workspace-cli
